llama_index/readers/agent_search/__init__.py
llama_index/readers/agent_search/base.py
llama_index_readers_agent_search-0.4.0.dist-info/METADATA
llama_index_readers_agent_search-0.4.0.dist-info/WHEEL
llama_index_readers_agent_search-0.4.0.dist-info/licenses/LICENSE
llama_index_readers_agent_search-0.4.0.dist-info/RECORD
